iripau/__init__.py
iripau/executable.py
iripau/functools.py
iripau/logging.py
iripau/random.py
iripau/requests.py
iripau/shutil.py
iripau/subprocess.py
iripau/threading.py
iripau/command/__init__.py
iripau-1.1.6.dist-info/licenses/LICENSE
iripau-1.1.6.dist-info/METADATA
iripau-1.1.6.dist-info/WHEEL
iripau-1.1.6.dist-info/top_level.txt
iripau-1.1.6.dist-info/RECORD
