Metadata-Version: 2.4
Name: iripau
Version: 1.1.6
Summary: Python utilities focused on command execution
Author: Ricardo Quezada
Maintainer: Ricardo Quezada
License-Expression: MPL-2.0
Project-URL: Documentation, https://ricardo-galo.github.io/iripau
Project-URL: Repository, https://github.com/ricardo-galo/iripau
Project-URL: Issues, https://github.com/ricardo-galo/iripau/issues
Project-URL: Changelog, https://github.com/ricardo-galo/iripau/blob/main/CHANGELOG.md
Keywords: subprocess,command,local,remote,ssh,Linux,real-time,log,logging,threading,utilities
Classifier: Development Status :: 5 - Production/Stable
Classifier: Programming Language :: Python
Requires-Python: >=3.7
License-File: LICENSE
Requires-Dist: curlify
Requires-Dist: psutil
Dynamic: license-file
